pywikiapi/Site.py
pywikiapi/__init__.py
pywikiapi/api.py
pywikiapi/utils.py
pywikiapi/version.py
pywikiapi-5.0.0.dist-info/LICENSE
pywikiapi-5.0.0.dist-info/METADATA
pywikiapi-5.0.0.dist-info/WHEEL
pywikiapi-5.0.0.dist-info/top_level.txt
pywikiapi-5.0.0.dist-info/RECORD
