Metadata-Version: 2.1
Name: pywikiapi
Version: 5.0.0
Summary: Tiny MediaWiki API client library from the author of the MW API
Home-page: https://github.com/nyurik/pywikiapi
Author: Yuri Astrakhan
Author-email: YuriAstrakhan@gmail.com
License: MIT
Classifier: License :: OSI Approved :: MIT License
Classifier: Intended Audience :: Developers
Classifier: Operating System :: OS Independent
Classifier: Programming Language :: Python
Classifier: Programming Language :: Python :: 3
Classifier: Programming Language :: Python :: 3.6
Classifier: Programming Language :: Python :: 3.7
Classifier: Programming Language :: Python :: 3.8
License-File: LICENSE
Requires-Dist: requests
Requires-Dist: responses
